djem/__init__.py
djem/ajax.py
djem/auth.py
djem/exceptions.py
djem/middleware.py
djem/pagination.py
djem/forms/__init__.py
djem/forms/bases.py
djem/forms/fields.py
djem/models/__init__.py
djem/models/fields.py
djem/models/models.py
djem/templates/djem/form_field.html
djem/templates/djem/pagination.html
djem/templates/djem/csrfify_ajax/jquery.html
djem/templatetags/__init__.py
djem/templatetags/djem.py
djem/tests/__init__.py
djem/tests/models.py
djem/tests/test_ajax.py
djem/tests/test_auth.py
djem/tests/test_forms.py
djem/tests/test_middleware.py
djem/tests/test_models.py
djem/tests/test_pagination.py
djem/tests/test_templatetags.py
djem/tests/test_utils.py
djem/utils/__init__.py
djem/utils/dev.py
djem/utils/dt.py
djem/utils/inspect.py
djem/utils/mon.py
djem/utils/table.py
djem/utils/tests.py
djem-0.8.0.dist-info/LICENSE
djem-0.8.0.dist-info/METADATA
djem-0.8.0.dist-info/WHEEL
djem-0.8.0.dist-info/top_level.txt
djem-0.8.0.dist-info/RECORD
