Metadata-Version: 2.1
Name: djem
Version: 0.8.0
Summary: A collection of useful stuff for Django projects
Home-page: https://github.com/oogles/djem
Author: Alex Church
Author-email: alex@church.id.au
License: BSD
Project-URL: Documentation, https://djem.readthedocs.io/en/latest/
Project-URL: Bug Tracker, https://github.com/oogles/djem/issues
Classifier: Environment :: Web Environment
Classifier: Framework :: Django
Classifier: Framework :: Django :: 3.2
Classifier: Framework :: Django :: 4.0
Classifier: Framework :: Django :: 4.1
Classifier: Intended Audience :: Developers
Classifier: License :: OSI Approved :: BSD License
Classifier: Operating System :: OS Independent
Classifier: Programming Language :: Python :: 3
Classifier: Programming Language :: Python :: 3.7
Classifier: Programming Language :: Python :: 3.8
Classifier: Programming Language :: Python :: 3.9
Classifier: Programming Language :: Python :: 3.10
Classifier: Programming Language :: Python :: 3.11
Requires-Python: >=3.7
License-File: LICENSE
Requires-Dist: Django (>=3.2)
